LICENSE
MANIFEST.in
README.md
requirements.txt
setup.cfg
setup.py
versioneer.py
pygran_sim/__init__.py
pygran_sim/_version.py
pygran_sim/base.py
pygran_sim/dem.py
pygran_sim/tools.py
pygran_sim.egg-info/PKG-INFO
pygran_sim.egg-info/SOURCES.txt
pygran_sim.egg-info/dependency_links.txt
pygran_sim.egg-info/not-zip-safe
pygran_sim.egg-info/requires.txt
pygran_sim.egg-info/top_level.txt
pygran_sim/engine/__init__.py
pygran_sim/engine/api.py
pygran_sim/engine/liggghts/__init__.py
pygran_sim/engine/liggghts/engine_liggghts.py
pygran_sim/engine/liggghts/input_liggghts.py
pygran_sim/engine/liggghts/model_liggghts.py
pygran_sim/engine/simple/__init__.py
pygran_sim/engine/simple/engine_simple.py
pygran_sim/engine/simple/input_simple.py