Metadata-Version: 2.1
Name: pygran-sim
Version: 1.1.0
Summary: A PyGran package for running DEM simulation
Home-page: https://github.com/Andrew-AbiMansour/PyGranSim
Author: Andrew Abi-Mansour
Author-email: support@pygran.org
License: GNU v2
Keywords: Discrete Element Method,Granular Materials
Classifier: Development Status :: 4 - Beta
Classifier: Topic :: Utilities
Classifier: License :: OSI Approved :: GNU General Public License v2 (GPLv2)
Classifier: Programming Language :: Python :: 3
Classifier: Programming Language :: Python :: 3.4
Classifier: Programming Language :: Python :: 3.5
Classifier: Programming Language :: Python :: 3.6
Classifier: Programming Language :: Python :: 3.7
Classifier: Operating System :: POSIX :: Linux
Provides-Extra: extras
Provides-Extra: tests
License-File: LICENSE
